pytest_lazyfixture-stubs/METADATA.toml
pytest_lazyfixture-stubs/__init__.pyi
types_pytest_lazy_fixture-0.6.3.20240310.dist-info/METADATA
types_pytest_lazy_fixture-0.6.3.20240310.dist-info/WHEEL
types_pytest_lazy_fixture-0.6.3.20240310.dist-info/top_level.txt
types_pytest_lazy_fixture-0.6.3.20240310.dist-info/RECORD
